timeflux_bitalino/__init__.py
timeflux_bitalino/helpers/__init__.py
timeflux_bitalino/helpers/transfer.py
timeflux_bitalino/nodes/__init__.py
timeflux_bitalino/nodes/driver.py
timeflux_bitalino-0.3.0.dist-info/LICENSE
timeflux_bitalino-0.3.0.dist-info/METADATA
timeflux_bitalino-0.3.0.dist-info/WHEEL
timeflux_bitalino-0.3.0.dist-info/top_level.txt
timeflux_bitalino-0.3.0.dist-info/RECORD
