Metadata-Version: 2.1
Name: timeflux-bitalino
Version: 0.3.0
Summary: Timeflux BITalino plugin
Home-page: https://timeflux.io
Author: Pierre Clisson
Author-email: contact@timeflux.io
License: MIT
Project-URL: Documentation, http://doc.timeflux.io/projects/timeflux-bitalino/
Project-URL: Source Code, https://github.com/timeflux/timeflux_bitalino
Project-URL: Bug Tracker, https://github.com/timeflux/timeflux_bitalino/issues
Keywords: timeflux,bitalino
Platform: UNKNOWN
Classifier: Development Status :: 4 - Beta
Classifier: Environment :: Console
Classifier: Intended Audience :: Developers
Classifier: Intended Audience :: Science/Research
Classifier: License :: OSI Approved :: MIT License
Classifier: Operating System :: OS Independent
Classifier: Programming Language :: Python
License-File: LICENSE
Requires-Dist: pyserial (>=3.4)
Requires-Dist: bitalino (>=1.2)
Requires-Dist: timeflux (>=0.5.3)
Provides-Extra: dev
Requires-Dist: pytest (>=5.3) ; extra == 'dev'
Requires-Dist: sphinx (>=2.2) ; extra == 'dev'
Requires-Dist: sphinx-rtd-theme (>=0.4) ; extra == 'dev'
Requires-Dist: setuptools-scm ; extra == 'dev'
Requires-Dist: docinit ; extra == 'dev'
